[{"ru":"протестовал","en":"protested","id":0},{"ru":"прикреплено","en":"tacked","id":1},{"ru":"усиленно трудиться","en":"toil","id":2},{"ru":"портрет","en":"portrait","id":3},{"ru":"стаут","en":"stout","id":4},{"ru":"непроверено","en":"unchecked","id":5},{"ru":"пальцы ног","en":"toes","id":6},{"ru":"осколок","en":"splinter","id":7},{"ru":"управляемый","en":"ruled","id":8},{"ru":"конституция","en":"constitution","id":9},{"ru":"вис","en":"vis","id":10},{"ru":"развязывание","en":"unleashing","id":11},{"ru":"настройка","en":"tweaking","id":12},{"ru":"болезнь","en":"sickness","id":13},{"ru":"возникает","en":"arises","id":14},{"ru":"канарейка","en":"canary","id":15},{"ru":"лесной пожар","en":"wildfire","id":16},{"ru":"министерский","en":"ministerial","id":17},{"ru":"на открытом воздухе","en":"outdoor","id":18},{"ru":"контакты","en":"contacts","id":19},{"ru":"спешка","en":"rush","id":20},{"ru":"местонахождение","en":"whereabouts","id":21},{"ru":"затуманенный","en":"clouded","id":22},{"ru":"оседланный","en":"saddled","id":23},{"ru":"учрежден","en":"instituted","id":24},{"ru":"мандат","en":"mandate","id":25},{"ru":"состоит","en":"constituted","id":26},{"ru":"продажа","en":"selling","id":27},{"ru":"привязан","en":"tethered","id":28},{"ru":"трансформаторы","en":"transformers","id":29},{"ru":"лекции","en":"lectures","id":30},{"ru":"полюс","en":"pole","id":31},{"ru":"семинары","en":"seminars","id":32},{"ru":"сложенный","en":"piled","id":33},{"ru":"утешил","en":"consoled","id":34},{"ru":"вниз","en":"downwards","id":35},{"ru":"позволять","en":"allow","id":36},{"ru":"благоприятный","en":"conducive","id":37},{"ru":"рассеивать","en":"disperse","id":38},{"ru":"интриги","en":"scheming","id":39},{"ru":"чистый","en":"pure","id":40},{"ru":"канонизация","en":"canonization","id":41},{"ru":"разблокирован","en":"unlocked","id":42},{"ru":"настойчивый","en":"insistent","id":43},{"ru":"смелый","en":"courageous","id":44},{"ru":"эффектный","en":"glamorous","id":45},{"ru":"гаечный ключ","en":"wrench","id":46},{"ru":"причинить","en":"inflict","id":47},{"ru":"подгонять","en":"prod","id":48},{"ru":"восклицая","en":"exclaiming","id":49},{"ru":"воображение","en":"imagination","id":50},{"ru":"врученный","en":"handed","id":51},{"ru":"обстоятельство","en":"circumstance","id":52},{"ru":"отскочил","en":"rebounded","id":53},{"ru":"меланома","en":"melanoma","id":54},{"ru":"бахрома","en":"fringe","id":55},{"ru":"подчиненные","en":"subordinates","id":56},{"ru":"красиво","en":"handsomely","id":57},{"ru":"химически","en":"chemically","id":58},{"ru":"медицинский","en":"med","id":59},{"ru":"стыки","en":"joints","id":60},{"ru":"судебная практика","en":"jurisprudence","id":61},{"ru":"тако","en":"tacos","id":62},{"ru":"умолять","en":"beseech","id":63},{"ru":"лекарства","en":"meds","id":64},{"ru":"измельченный","en":"shredded","id":65},{"ru":"невеста","en":"fiancee","id":66},{"ru":"задушены","en":"smothered","id":67},{"ru":"морщины","en":"wrinkles","id":68},{"ru":"конкуренты","en":"rivals","id":69},{"ru":"двоюродный брат","en":"cousin","id":70},{"ru":"обожание","en":"adoration","id":71},{"ru":"захлопывать","en":"slam","id":72},{"ru":"сезон","en":"season","id":73},{"ru":"опубликованный","en":"posted","id":74},{"ru":"отвратительный","en":"heinous","id":75},{"ru":"нехватка","en":"lacks","id":76},{"ru":"заинтересованный","en":"interested","id":77},{"ru":"упомянутый","en":"outlined","id":78},{"ru":"оплачиваемый","en":"paid","id":79},{"ru":"любящий","en":"loving","id":80},{"ru":"точка опоры","en":"foothold","id":81},{"ru":"полярный","en":"polar","id":82},{"ru":"хваленая","en":"vaunted","id":83},{"ru":"анализы","en":"analyses","id":84},{"ru":"запинаясь","en":"faltering","id":85},{"ru":"роза","en":"rose","id":86},{"ru":"полностью","en":"wholly","id":87},{"ru":"эксплуатация","en":"exploitation","id":88},{"ru":"пройденный","en":"traversed","id":89},{"ru":"заброшенный","en":"forlorn","id":90},{"ru":"неизменившийся","en":"unchanged","id":91},{"ru":"недовольство","en":"discontent","id":92},{"ru":"невероятно","en":"unbelievable","id":93},{"ru":"буквы","en":"letters","id":94},{"ru":"взаимодействие","en":"interacting","id":95},{"ru":"облегченный","en":"lightened","id":96},{"ru":"прочность","en":"toughness","id":97},{"ru":"вирулентный","en":"virulent","id":98},{"ru":"преданность","en":"dedication","id":99},{"ru":"освещенный","en":"lighted","id":100},{"ru":"колбасы","en":"sausages","id":101},{"ru":"мнение","en":"opinion","id":102},{"ru":"батареи","en":"batteries","id":103},{"ru":"дополнительный","en":"subsidiary","id":104},{"ru":"разорвал","en":"tore","id":105},{"ru":"не определено","en":"undetermined","id":106},{"ru":"горшки","en":"pots","id":107},{"ru":"не хватало","en":"lacked","id":108},{"ru":"встречающийся","en":"encountered","id":109},{"ru":"порванный","en":"torn","id":110},{"ru":"запрошенный","en":"inquired","id":111},{"ru":"ортодоксальный","en":"orthodox","id":112},{"ru":"ранее","en":"previously","id":113},{"ru":"постоянная ссылка","en":"permalink","id":114},{"ru":"воспринимая","en":"perceiving","id":115},{"ru":"запросил","en":"queried","id":116},{"ru":"покрытый","en":"plated","id":117},{"ru":"отправление","en":"departure","id":118},{"ru":"идеализм","en":"idealism","id":119},{"ru":"пошатнувшийся","en":"shaken","id":120},{"ru":"достигать","en":"achieve","id":121},{"ru":"подтягивающий","en":"tightening","id":122},{"ru":"щелчки","en":"flicks","id":123},{"ru":"опьянение","en":"intoxication","id":124},{"ru":"сокращать","en":"shorten","id":125},{"ru":"распространение","en":"dissemination","id":126},{"ru":"застава","en":"outpost","id":127},{"ru":"такелаж","en":"rigging","id":128},{"ru":"подсказки","en":"hints","id":129},{"ru":"презрение","en":"scorn","id":130},{"ru":"составить","en":"compose","id":131},{"ru":"адрес","en":"worded","id":132},{"ru":"удовлетворительный","en":"satisfying","id":133},{"ru":"устанавливает","en":"establishes","id":134},{"ru":"состоящий","en":"consisting","id":135},{"ru":"фермерский дом","en":"farmhouse","id":136},{"ru":"тощий","en":"gaunt","id":137},{"ru":"потекло","en":"flowed","id":138},{"ru":"арендованный","en":"rented","id":139},{"ru":"воздействие","en":"exposure","id":140},{"ru":"успешный","en":"succeed","id":141},{"ru":"состоит","en":"constituted","id":142},{"ru":"кражи","en":"thefts","id":143},{"ru":"ошибки","en":"lapses","id":144},{"ru":"зрелость","en":"maturity","id":145},{"ru":"кабинет","en":"cabinet","id":146},{"ru":"холестерин","en":"cholesterol","id":147},{"ru":"изобретательный","en":"ingenious","id":148},{"ru":"доброкачественный","en":"benign","id":149},{"ru":"видеокамера","en":"camcorder","id":150},{"ru":"велосипедист","en":"cyclist","id":151},{"ru":"номинальный","en":"nominal","id":152},{"ru":"юго-запад","en":"southwest","id":153},{"ru":"тизер","en":"teaser","id":154},{"ru":"спонсорство","en":"sponsorships","id":155},{"ru":"оруженосец","en":"squire","id":156},{"ru":"пловец","en":"swimmer","id":157},{"ru":"эскиз","en":"thumbnail","id":158},{"ru":"обитатели","en":"dwellers","id":159},{"ru":"порванный","en":"torn","id":160},{"ru":"чувства","en":"feelings","id":161},{"ru":"жизнеспособность","en":"viability","id":162},{"ru":"развлекательный","en":"entertaining","id":163},{"ru":"ускорился","en":"quickened","id":164},{"ru":"сокращенно","en":"abbreviated","id":165},{"ru":"переработка","en":"refinery","id":166},{"ru":"сошлись","en":"converged","id":167},{"ru":"облегченный","en":"lightened","id":168},{"ru":"капитализация","en":"capitalization","id":169},{"ru":"женщины","en":"females","id":170},{"ru":"трение","en":"rubbing","id":171},{"ru":"разногласие","en":"dissent","id":172},{"ru":"собрания","en":"congregations","id":173},{"ru":"сбор средств","en":"fundraisers","id":174},{"ru":"печать","en":"seal","id":175},{"ru":"вниз","en":"downwards","id":176},{"ru":"разбили лагерь","en":"encamped","id":177},{"ru":"место хранения","en":"storage","id":178},{"ru":"сахара","en":"sugars","id":179},{"ru":"поставщик","en":"supplier","id":180},{"ru":"нарушения","en":"breaches","id":181},{"ru":"наглый","en":"impertinent","id":182},{"ru":"особенности","en":"features","id":183},{"ru":"русские","en":"russians","id":184},{"ru":"концентрированный","en":"concentrated","id":185},{"ru":"дверной проем","en":"doorway","id":186},{"ru":"предъявлено обвинение","en":"indicted","id":187},{"ru":"запоздалый","en":"belated","id":188},{"ru":"эпидемии","en":"plagues","id":189},{"ru":"мистический","en":"mystical","id":190},{"ru":"застывший","en":"stark","id":191},{"ru":"миграция","en":"migrating","id":192},{"ru":"рулетка","en":"roulette","id":193},{"ru":"творчески","en":"creatively","id":194},{"ru":"болезнь","en":"disease","id":195},{"ru":"влиять","en":"affect","id":196},{"ru":"парализованный","en":"paralyzed","id":197},{"ru":"весло","en":"oar","id":198},{"ru":"без усилий","en":"effortlessly","id":199},{"ru":"кандидаты","en":"candidates","id":200},{"ru":"геология","en":"geology","id":201},{"ru":"освещенный","en":"lighted","id":202},{"ru":"выскочка","en":"upstart","id":203},{"ru":"указ","en":"edict","id":204},{"ru":"бабушки","en":"grandmothers","id":205},{"ru":"зонтик","en":"umbrella","id":206},{"ru":"толкнул","en":"pushed","id":207},{"ru":"курс","en":"course","id":208},{"ru":"одиночество","en":"loneliness","id":209},{"ru":"область","en":"realm","id":210},{"ru":"порванный","en":"torn","id":211},{"ru":"деталь","en":"detail","id":212},{"ru":"метать","en":"hurl","id":213},{"ru":"палуба","en":"deck","id":214},{"ru":"отчуждать","en":"alienate","id":215},{"ru":"нарушение","en":"breach","id":216},{"ru":"с обнаженной грудью","en":"topless","id":217},{"ru":"хор","en":"choir","id":218},{"ru":"выращенный","en":"cultivated","id":219},{"ru":"серферы","en":"surfers","id":220},{"ru":"в порядке","en":"alright","id":221},{"ru":"приснившийся","en":"dreamed","id":222},{"ru":"высохший","en":"withered","id":223},{"ru":"обстоятельство","en":"circumstance","id":224},{"ru":"скоростной","en":"speedy","id":225},{"ru":"исследование","en":"researching","id":226},{"ru":"республика","en":"republic","id":227},{"ru":"кондиционер","en":"conditioner","id":228},{"ru":"стихи","en":"poems","id":229},{"ru":"борьба с загрязнением","en":"abatement","id":230},{"ru":"запутывать","en":"tangle","id":231},{"ru":"биполярный","en":"bipolar","id":232},{"ru":"жаловаться","en":"complain","id":233},{"ru":"принтер","en":"printer","id":234},{"ru":"десерт","en":"dessert","id":235},{"ru":"инструктор","en":"instructor","id":236},{"ru":"сочилась","en":"trickled","id":237},{"ru":"стихи","en":"verses","id":238},{"ru":"лекции","en":"lectures","id":239},{"ru":"прослушивание","en":"audition","id":240},{"ru":"партнерские отношения","en":"partnerships","id":241},{"ru":"блеск","en":"luster","id":242},{"ru":"бахрома","en":"fringe","id":243},{"ru":"вибрируя","en":"vibrating","id":244},{"ru":"замечательный","en":"admirable","id":245},{"ru":"друзья","en":"friends","id":246},{"ru":"происходить","en":"occur","id":247},{"ru":"объявления","en":"announcements","id":248},{"ru":"княжеский","en":"princely","id":249},{"ru":"возникать","en":"arise","id":250},{"ru":"надувать","en":"inflate","id":251},{"ru":"достигать","en":"attain","id":252},{"ru":"встретились","en":"met","id":253},{"ru":"профили","en":"profiles","id":254},{"ru":"штормы","en":"storms","id":255},{"ru":"не нравится","en":"dislikes","id":256},{"ru":"несообразность","en":"inconsistency","id":257},{"ru":"причинение","en":"inflicting","id":258},{"ru":"сокращать","en":"shorten","id":259},{"ru":"слова","en":"words","id":260},{"ru":"утонул","en":"drowned","id":261},{"ru":"фоны","en":"backgrounds","id":262},{"ru":"пауки","en":"spiders","id":263},{"ru":"издатель","en":"publisher","id":264},{"ru":"пророчество","en":"prophecy","id":265},{"ru":"кандидаты","en":"candidates","id":266},{"ru":"барометр","en":"barometer","id":267},{"ru":"катастрофа","en":"catastrophe","id":268},{"ru":"градуированный","en":"graded","id":269},{"ru":"сдается в аренду","en":"leased","id":270},{"ru":"бомбардировка","en":"bombardment","id":271},{"ru":"красочный","en":"colorful","id":272},{"ru":"лицо","en":"visage","id":273},{"ru":"кокпит","en":"cockpit","id":274},{"ru":"национализм","en":"nationalism","id":275},{"ru":"коэффициенты","en":"ratios","id":276},{"ru":"бесконечно","en":"endlessly","id":277},{"ru":"оснащен","en":"outfitted","id":278},{"ru":"самый короткий","en":"shortest","id":279},{"ru":"прекратить","en":"terminate","id":280},{"ru":"долгота","en":"longitude","id":281},{"ru":"бон","en":"bon","id":282},{"ru":"министерский","en":"ministerial","id":283},{"ru":"фармацевтические препараты","en":"pharmaceuticals","id":284},{"ru":"сокращать","en":"shorten","id":285},{"ru":"оргазм","en":"orgasm","id":286},{"ru":"избыток","en":"excess","id":287},{"ru":"спад","en":"downturn","id":288},{"ru":"педаль","en":"pedal","id":289},{"ru":"новичок","en":"novice","id":290},{"ru":"тщеславие","en":"conceit","id":291},{"ru":"вращение","en":"rotation","id":292},{"ru":"отцы","en":"fathers","id":293},{"ru":"проснуться","en":"awake","id":294},{"ru":"материализм","en":"materialism","id":295},{"ru":"орудуя","en":"wielding","id":296},{"ru":"литература","en":"literature","id":297},{"ru":"ясность","en":"clearness","id":298},{"ru":"отложение","en":"deposition","id":299},{"ru":"с тоской","en":"wistfully","id":300},{"ru":"прочтение","en":"perusal","id":301},{"ru":"огромный","en":"tremendous","id":302},{"ru":"пословица","en":"proverb","id":303},{"ru":"лингвистика","en":"linguistics","id":304},{"ru":"воспроизведено","en":"reproduced","id":305},{"ru":"заросли","en":"thicket","id":306},{"ru":"тяга","en":"traction","id":307},{"ru":"хваленая","en":"vaunted","id":308},{"ru":"котелки","en":"bowlers","id":309},{"ru":"вводящий в заблуждение","en":"misleading","id":310},{"ru":"неправильный","en":"incorrect","id":311},{"ru":"супы","en":"soups","id":312},{"ru":"берущие","en":"takers","id":313},{"ru":"сомнительный","en":"doubtful","id":314},{"ru":"цели","en":"goals","id":315},{"ru":"запросил","en":"queried","id":316},{"ru":"лесистая местность","en":"woodland","id":317},{"ru":"имело значение","en":"mattered","id":318},{"ru":"бункеры","en":"bins","id":319},{"ru":"приход","en":"parish","id":320},{"ru":"дуга","en":"arc","id":321},{"ru":"посредническая","en":"brokered","id":322},{"ru":"неоднозначность","en":"ambiguity","id":323},{"ru":"высказал мнение","en":"opined","id":324},{"ru":"взносы","en":"contributions","id":325},{"ru":"правонарушения","en":"offences","id":326},{"ru":"упомянутый","en":"mentioned","id":327},{"ru":"перевернутый","en":"inverted","id":328},{"ru":"биопсия","en":"biopsy","id":329},{"ru":"зарянка","en":"robin","id":330},{"ru":"миниатюры","en":"miniatures","id":331},{"ru":"предпочтительный","en":"preferred","id":332},{"ru":"выдержки","en":"extracts","id":333},{"ru":"бакалавр","en":"bachelor","id":334},{"ru":"освежающий","en":"refreshing","id":335},{"ru":"черника","en":"blueberries","id":336},{"ru":"разбавленный","en":"diluted","id":337},{"ru":"балансировка","en":"balancing","id":338},{"ru":"трансформация","en":"transforming","id":339},{"ru":"мученики","en":"martyrs","id":340},{"ru":"десятый","en":"tenth","id":341},{"ru":"грант","en":"grant","id":342},{"ru":"оценка","en":"appraisal","id":343},{"ru":"в порядке","en":"alright","id":344},{"ru":"завязывание","en":"tying","id":345},{"ru":"безделушки","en":"trinkets","id":346},{"ru":"переходы","en":"transitions","id":347},{"ru":"захмелевший","en":"sprung","id":348},{"ru":"утверждает","en":"contends","id":349},{"ru":"бич","en":"scourge","id":350},{"ru":"сточные воды","en":"wastewater","id":351},{"ru":"нарушение","en":"breach","id":352},{"ru":"часто посещаемый","en":"frequented","id":353},{"ru":"скобы","en":"staples","id":354},{"ru":"запуск","en":"startup","id":355},{"ru":"привлекательный","en":"appealing","id":356},{"ru":"подготовка","en":"preparation","id":357},{"ru":"непригодный","en":"unfit","id":358},{"ru":"освещенный","en":"lighted","id":359},{"ru":"приходы","en":"parishes","id":360},{"ru":"вакансия","en":"vacancy","id":361},{"ru":"птицы","en":"fowls","id":362},{"ru":"шокер","en":"shocker","id":363},{"ru":"воображаемый","en":"imaginable","id":364},{"ru":"холдинги","en":"holdings","id":365},{"ru":"рейдеры","en":"raiders","id":366},{"ru":"шаблон","en":"pattern","id":367},{"ru":"уподобился","en":"likened","id":368},{"ru":"дисплеи","en":"displays","id":369},{"ru":"снежный","en":"snowy","id":370},{"ru":"состоит","en":"constituted","id":371},{"ru":"регулирующий","en":"adjusting","id":372},{"ru":"персона","en":"persona","id":373},{"ru":"целевые","en":"earmarked","id":374},{"ru":"застенчивый","en":"blushing","id":375},{"ru":"излучаемый","en":"beamed","id":376},{"ru":"мосты","en":"bridges","id":377},{"ru":"оттенок","en":"tinge","id":378},{"ru":"кабинет","en":"parlor","id":379},{"ru":"гипертония","en":"hypertension","id":380},{"ru":"тюрьмы","en":"jails","id":381},{"ru":"кредит","en":"loan","id":382},{"ru":"алфавит","en":"alphabet","id":383},{"ru":"вереск","en":"heath","id":384},{"ru":"преуспел","en":"excelled","id":385},{"ru":"телевизоры","en":"tvs","id":386},{"ru":"беспрецедентный","en":"unprecedented","id":387},{"ru":"доверено","en":"entrusted","id":388},{"ru":"аспект","en":"aspect","id":389},{"ru":"равнины","en":"plains","id":390},{"ru":"датчик","en":"sensor","id":391},{"ru":"торговый центр","en":"mall","id":392},{"ru":"уплотненный","en":"packed","id":393},{"ru":"постановка","en":"staging","id":394},{"ru":"однообразный","en":"drab","id":395},{"ru":"курс","en":"course","id":396},{"ru":"министерство","en":"ministry","id":397},{"ru":"опыт","en":"experiences","id":398}]